{
  "Description.ja": "\u6DF1\u591C\u306E\u30AA\u30D5\u30A3\u30B9\u306E\u3088\u3046\u306A\u9759\u5BC2\u3068\u3001\u9AD8\u5EA6\u306A\u60C5\u5831\u51E6\u7406\u3092\u30A4\u30E1\u30FC\u30B8\u3057\u305F\u6FC3\u7D3A",
  "Description.en": "A deep navy evoking the silence of a late-night office and advanced information processing",
  "Description.zh-CN": "\u6DF1\u9083\u85CF\u9752\u8272\uFF0C\u5524\u8D77\u6DF1\u591C\u529E\u516C\u5BA4\u7684\u5BC2\u9759\u4E0E\u9AD8\u7EA7\u4FE1\u606F\u5904\u7406\u7684\u6C1B\u56F4",
  "Description.zh-TW": "\u6DF1\u9083\u85CF\u9752\u8272\uFF0C\u559A\u8D77\u6DF1\u591C\u8FA6\u516C\u5BA4\u7684\u5BC2\u975C\u8207\u9AD8\u7D1A\u8CC7\u8A0A\u8655\u7406\u7684\u6C1B\u570D",
  "Description.ko-KR": "\uC2EC\uC57C \uC0AC\uBB34\uC2E4\uC758 \uC815\uC801\uACFC \uACE0\uAE09 \uC815\uBCF4 \uCC98\uB9AC\uB97C \uC5F0\uC0C1\uC2DC\uD0A4\uB294 \uAE4A\uC740 \uB124\uC774\uBE44",
  "Description.de": "Ein tiefes Navy, das die Stille eines B\u00FCros bei Nacht und fortgeschrittene Datenverarbeitung hervorruft",
  "Description.es": "Un azul marino profundo que evoca el silencio de una oficina nocturna y el procesamiento avanzado de informaci\u00F3n",
  "Description.fr": "Un bleu marine profond \u00E9voquant le silence d\u0027un bureau de nuit et le traitement avanc\u00E9 de l\u0027information",
  "Description.ru": "\u0413\u043B\u0443\u0431\u043E\u043A\u0438\u0439 \u0442\u0451\u043C\u043D\u043E-\u0441\u0438\u043D\u0438\u0439, \u0432\u044B\u0437\u044B\u0432\u0430\u044E\u0449\u0438\u0439 \u0442\u0438\u0448\u0438\u043D\u0443 \u043D\u043E\u0447\u043D\u043E\u0433\u043E \u043E\u0444\u0438\u0441\u0430 \u0438 \u0430\u0442\u043C\u043E\u0441\u0444\u0435\u0440\u0443 \u043E\u0431\u0440\u0430\u0431\u043E\u0442\u043A\u0438 \u0434\u0430\u043D\u043D\u044B\u0445",
  "Description.pt": "Um azul-marinho profundo que evoca o sil\u00EAncio de um escrit\u00F3rio noturno e o processamento avan\u00E7ado de informa\u00E7\u00F5es",
  "Author": "K.AKASAKA",
  "Category": "Professional",
  "UpdatedAt": "2026-07-18T17:40:53Z",
  "Base": {
    "BackgroundColor": "#10151C",
    "PropertyPathBackgroundColor": "#10151C",
    "SidebarColor": "#1B212A",
    "HeaderColor": "#1A212B",
    "TitleBarColor": "#1B212A",
    "TitleBarTextColor": "#C9D6E4",
    "BorderColor": "#30363D",
    "ListGridLineColor": "#243143",
    "PropertyPathBorderColor": "#30363D",
    "PrimaryTextColor": "#BFD6F2",
    "ChallengeNameTextColor": "#BFD6F2",
    "AddressBarTextColor": "#BFD6F2",
    "AddressBarSeparatorColor": "#BFD6F2",
    "TabLabelTextColor": "#BFD6F2",
    "SidebarTextColor": "#BFD6F2",
    "SettingsMenuTextColor": "#BFD6F2",
    "SettingsMenuSelectedTextColor": "#BFD6F2",
    "SettingsMenuHoverTextColor": "#BFD6F2",
    "DestructiveHoverTextColor": "#FBEAEA",
    "ChallengeCardTextColor": "#BFD6F2",
    "DeckItemSelectedTextColor": "#BFD6F2",
    "DeckItemHoverTextColor": "#BFD6F2",
    "FilterChipTextColor": "#BFD6F2",
    "FilterToggleCheckedTextColor": "#EAF2FC",
    "OptionSelectedHoverTextColor": "#EAF2FC",
    "CheckboxHoverTextColor": "#BFD6F2",
    "ButtonIdleTextColor": "#BFD6F2",
    "ButtonHoverTextColor": "#BFD6F2",
    "InactiveSelectionTextColor": "#BFD6F2",
    "SelectionTextColor": "#EAF2FC",
    "StatusBarTextColor": "#BFD6F2",
    "SecondaryTextColor": "#6F7782",
    "NavSectionHeaderColor": "#6F7782",
    "PreviewPanelTextColor": "#6F7782",
    "FileListHeaderColor": "#6F7782",
    "SidebarIconColor": "#7E8894",
    "IconForegroundColor": "#7E8894",
    "InputBackgroundColor": "#0A0E14",
    "FocusedPaneBackgroundColor": "#151B24",
    "FocusedPaneHeaderBackgroundColor": "#1F242C",
    "OnePointDarkColor": "#1F2937",
    "OnePointDarkTextColor": "#BFD6F2",
    "TabSeparatorColor": "#30363D",
    "TabHoverColor": "#252B35",
    "ToolbarSeparatorColor": "#30363D",
    "TreeLineColor": "#30363D",
    "PopupBackgroundColor": "#1B212A",
    "PopupTextColor": "#C9D6E4",
    "PopupHoverBackgroundColor": "#252C36",
    "PopupHoverTextColor": "#BFD6F2"
  },
  "List": {
    "ListHoverColor": "#252B35",
    "SelectionColor": "#22405E",
    "SettingsMenuSelectedColor": "#22405E",
    "SettingsMenuHoverColor": "#7222405E",
    "ButtonHoverColor": "#242B34",
    "InactiveSelectionColor": "#1B212A",
    "OptionSelectedColor": "#22405E",
    "OptionSelectedHoverColor": "#2F5177",
    "CheckboxHoverColor": "#7F9DBC",
    "CheckedHoverAccentColor": "#8AA8C6",
    "FilterActiveIndicatorColor": "#6584A3",
    "FilterChipBackgroundColor": "#21262D",
    "FilterChipBorderColor": "#30363D",
    "FilterToggleCheckedBackgroundColor": "#22405E",
    "ButtonIdleColor": "#1B212A"
  },
  "Search": {
    "IndexSearchBackgroundColor": "#10151C",
    "IndexSearchIconColor": "#D6B15A",
    "IndexSearchFocusBorderColor": "#22405E",
    "SearchModeNormalBackgroundColor": "#22405E",
    "SearchModeNormalTextColor": "#EAF2FC",
    "SearchModeGrepBackgroundColor": "#2C5240",
    "SearchModeGrepTextColor": "#E4F3EA",
    "SearchModeIndexBackgroundColor": "#5A4A22",
    "SearchModeIndexTextColor": "#F4ECD8",
    "SearchModeFilterBackgroundColor": "#3B3468",
    "SearchModeFilterTextColor": "#E9E5F6",
    "NormalSearchIconColor": "#8FB0D4",
    "NormalSearchBackgroundColor": "#10151C",
    "NormalSearchFocusBorderColor": "#22405E",
    "GrepSearchIconColor": "#6FBF8E",
    "GrepSearchBackgroundColor": "#10151C",
    "GrepSearchFocusBorderColor": "#2C5240",
    "FilterSearchIconColor": "#9A8FD6",
    "FilterSearchBackgroundColor": "#10151C",
    "FilterSearchFocusBorderColor": "#3B3468"
  },
  "Accent": {
    "AccentColor": "#6584A3",
    "ErrorTextColor": "#F27168",
    "DestructiveHoverBackgroundColor": "#DA3633",
    "DestructiveIconColor": "#F27168",
    "SuccessColor": "#4BB463"
  },
  "ContextMenu": {
    "ContextMenuSeparatorColor": "#30363D",
    "ContextMenuBackgroundColor": "#1B212A",
    "ContextMenuBorderColor": "#444C56",
    "ContextMenuTextColor": "#C9D6E4",
    "ContextMenuIconColor": "#8B97A6",
    "ContextMenuShortcutColor": "#6E7681",
    "ContextMenuDisabledColor": "#484F58",
    "ContextMenuDisabledIconColor": "#484F58",
    "ContextMenuHighlightShortcutColor": "#BFD6F2",
    "ContextMenuOuterBackgroundColor": "#10151C"
  },
  "Misc": {
    "GlowBarGlowColor": "#6584A3",
    "ScanBarColor": "#6584A3",
    "LoadingOverlayColor": "#CC0D1117",
    "ShadowColor": "#000000",
    "TelemetryBackgroundColor": "#E6161B22",
    "TelemetryBorderColor": "#30363D",
    "TelemetryTitleColor": "#6584A3",
    "TelemetryValueColor": "#C9D6E4",
    "PreviewPanelBorderColor": "#30363D",
    "PreviewPdfBackgroundColor": "#10151C",
    "IndexStatusNormalColor": "#8B97A6",
    "IndexStatusWarmColor": "#D29922",
    "AiBadgeColor": "#A371F7",
    "ProBadgeColor": "#6584A3",
    "DeckItemHoverColor": "#242B34",
    "ChallengeCardColor": "#1B212A",
    "ChallengeCardCompletedColor": "#5C7C9C",
    "ChallengeCardCompletedTextColor": "#EAF2FC",
    "DialogButtonColor": "#21262D",
    "DialogButtonTextColor": "#BFD6F2",
    "DialogButtonHoverColor": "#30363D",
    "DialogPrimaryButtonColor": "#22405E",
    "DialogPrimaryButtonTextColor": "#EAF2FC",
    "DialogPrimaryButtonHoverColor": "#2F5177",
    "LevelBadgeColor": "#6584A3",
    "LevelBadgeTextColor": "#0A0E14",
    "TitleBadgeColor": "#6584A3",
    "TitleBadgeTextColor": "#0A0E14",
    "ProBadgeTextColor": "#0A0E14",
    "TitleBarIconHoverColor": "#6584A3",
    "StickmanColor": "#6584A3",
    "StickmanPreviewBackgroundColor": "#30363D",
    "FavoriteStarColor": "#D6B15A",
    "GoldAccentColor": "#C4A03C",
    "OverlayBackgroundColor": "#A0000000",
    "OverlayTextColor": "#E0E0E0",
    "SubtleGlassColor": "#30FFFFFF",
    "WindowOuterBorderColor": "#00000000"
  },
  "NavPane": {
    "NavItemColor": "#1B212A",
    "NavItemTextColor": "#C9D6E4",
    "NavItemHoverColor": "#252C36",
    "NavItemHoverTextColor": "#BFD6F2",
    "NavItemSelectedColor": "#22405E",
    "NavItemSelectedTextColor": "#EAF2FC",
    "DeckItemSelectedColor": "#22405E"
  }
}